benchwork/__init__.py
benchwork/api.py
benchwork/case.py
benchwork/set_.py
benchwork/suite.py
benchwork/utils.py
benchwork-0.0.2.dist-info/WHEEL
benchwork-0.0.2.dist-info/METADATA
benchwork-0.0.2.dist-info/RECORD
